fastapi_auth_oidc/__init__.py
fastapi_auth_oidc/exceptions.py
fastapi_auth_oidc/provider.py
fastapi_auth_oidc/settings.py
fastapi_auth_oidc/types.py
fastapi_auth_oidc-0.1.5.dist-info/licenses/LICENSE.txt
fastapi_auth_oidc-0.1.5.dist-info/METADATA
fastapi_auth_oidc-0.1.5.dist-info/WHEEL
fastapi_auth_oidc-0.1.5.dist-info/top_level.txt
fastapi_auth_oidc-0.1.5.dist-info/RECORD
