Metadata-Version: 2.4
Name: fastapi_auth_oidc
Version: 0.1.5
Summary: FastAPI Auth OpenID Connect
Author-email: "DYAKOV.SPACE" <admin@dyakov.space>, Roman Dyakov <roman@dyakov.space>
License: BSD 3-Clause
Project-URL: Homepage, https://git.dyakov.space/dyakovri/fastapi-auth-oidc
Project-URL: Documentation, https://git.dyakov.space/dyakovri/fastapi-auth-oidc/wiki
Project-URL: Repository, https://git.dyakov.space/dyakovri/fastapi-auth-oidc
Project-URL: Issues, https://git.dyakov.space/dyakovri/fastapi-auth-oidc/issues
Project-URL: Changelog, https://git.dyakov.space/dyakovri/fastapi-auth-oidc/releases
Classifier: Development Status :: 4 - Beta
Classifier: Programming Language :: Python :: 3
Classifier: Programming Language :: Python :: 3.11
Classifier: Programming Language :: Python :: 3.12
Requires-Python: >=3.11
License-File: LICENSE.txt
Requires-Dist: fastapi
Requires-Dist: cachetools>=6.1.0
Requires-Dist: requests
Requires-Dist: python-jose[cryptography]>=3.5.0
Dynamic: license-file
